README.md
setup.py
src/simplelayout/__init__.py
src/simplelayout/__main__.py
src/simplelayout/cli/__init__.py
src/simplelayout/cli/cli_generate.py
src/simplelayout/generator/__init__.py
src/simplelayout/generator/core.py
src/simplelayout/generator/utils.py
src/simplelayout_a10213470.egg-info/PKG-INFO
src/simplelayout_a10213470.egg-info/SOURCES.txt
src/simplelayout_a10213470.egg-info/dependency_links.txt
src/simplelayout_a10213470.egg-info/entry_points.txt
src/simplelayout_a10213470.egg-info/requires.txt
src/simplelayout_a10213470.egg-info/top_level.txt