Metadata-Version: 2.1
Name: simplelayout-a10213470
Version: 0.0.1
Summary: a layout package
Home-page: UNKNOWN
Author: miraqiaox
Author-email: miraqiaox@qq.com
License: UNKNOWN
Platform: UNKNOWN
Classifier: Programming Language :: Python :: 3
Classifier: License :: OSI Approved :: MIT License
Classifier: Operating System :: OS Independent
Requires-Python: >=3.6
